{
  "posts": [
    {
      "id": 1,
      "title": "json-server",
      "author": "typicode"
    },
    {
      "firstname": "dao",
      "lastname": "tuan",
      "phonenumber": "095551414",
      "city": "da nang",
      "id": 2
    },
    {
      "firstname": "dao",
      "lastname": "tuan",
      "phonenumber": "54654213",
      "city": "nghe ",
      "id": 3
    }
  ],
  "signup": [
    {
      "name": "tuan",
      "email": "oke121@gmail.com",
      "password": "123456",
      "id": 1
    }
  ],
  "profile": {
    "name": "typicode"
  }
}